{
  "dark": {
    "cPrimary": "#76946a",
    "cOnPrimary": "#1f1f28",
    "cSecondary": "#c0a36e",
    "cOnSecondary": "#1f1f28",
    "cTertiary": "#7e9cd8",
    "cOnTertiary": "#1f1f28",
    "cError": "#c34043",
    "cOnError": "#1f1f28",
    "cSurface": "#1f1f28",
    "cOnSurface": "#c8c093",
    "cSurfaceVariant": "#2a2a37",
    "cOnSurfaceVariant": "#717c7c",
    "cOutline": "#363646",
    "cShadow": "#1f1f28",
    "cHover": "#7e9cd8",
    "cOnHover": "#1f1f28",
    "terminal": {
      "normal": {
        "black": "#090618",
        "red": "#c34043",
        "green": "#76946a",
        "yellow": "#c0a36e",
        "blue": "#7e9cd8",
        "magenta": "#957fb8",
        "cyan": "#6a9589",
        "white": "#c8c093"
      },
      "bright": {
        "black": "#727169",
        "red": "#e82424",
        "green": "#98bb6c",
        "yellow": "#e6c384",
        "blue": "#7fb4ca",
        "magenta": "#938aa9",
        "cyan": "#7aa89f",
        "white": "#dcd7ba"
      },
      "foreground": "#dcd7ba",
      "background": "#1f1f28",
      "selectionFg": "#c8c093",
      "selectionBg": "#2d4f67",
      "cursorText": "#1f1f28",
      "cursor": "#c8c093"
    }
  },
  "light": {
    "cPrimary": "#6f894e",
    "cOnPrimary": "#f2ecbc",
    "cSecondary": "#77713f",
    "cOnSecondary": "#f2ecbc",
    "cTertiary": "#4d699b",
    "cOnTertiary": "#f2ecbc",
    "cError": "#c84053",
    "cOnError": "#f2ecbc",
    "cSurface": "#f2ecbc",
    "cOnSurface": "#545464",
    "cSurfaceVariant": "#e5ddb0",
    "cOnSurfaceVariant": "#8a8980",
    "cOutline": "#cfc49c",
    "cShadow": "#f2ecbc",
    "cHover": "#4d699b",
    "cOnHover": "#f2ecbc",
    "terminal": {
      "normal": {
        "black": "#1F1F28",
        "red": "#c84053",
        "green": "#6f894e",
        "yellow": "#77713f",
        "blue": "#4d699b",
        "magenta": "#b35b79",
        "cyan": "#597b75",
        "white": "#545464"
      },
      "bright": {
        "black": "#8a8980",
        "red": "#d7474b",
        "green": "#6e915f",
        "yellow": "#836f4a",
        "blue": "#6693bf",
        "magenta": "#624c83",
        "cyan": "#5e857a",
        "white": "#43436c"
      },
      "foreground": "#545464",
      "background": "#f2ecbc",
      "selectionFg": "#f2ecbc",
      "selectionBg": "#c9cbd1",
      "cursorText": "#f2ecbc",
      "cursor": "#43436c"
    }
  }
}